metadisassembler/Compound.py
metadisassembler/Library.py
metadisassembler/MetaDisassembler.py
metadisassembler/__init__.py
metadisassembler/data/bul.pickle
metadisassembler-0.1.0.dist-info/LICENSE
metadisassembler-0.1.0.dist-info/METADATA
metadisassembler-0.1.0.dist-info/WHEEL
metadisassembler-0.1.0.dist-info/entry_points.txt
metadisassembler-0.1.0.dist-info/top_level.txt
metadisassembler-0.1.0.dist-info/RECORD
