Metadata-Version: 2.1
Name: metadisassembler
Version: 0.1.0
Summary: The Metabolic Disassembler
Home-page: https://github.com/the-metabolic-disassembler/metadisassembler
Author: Kohei Amano
Author-email: amanok2167@gmail.com
Maintainer: Masaaki Kotera
Maintainer-email: maskot1977@gmail.com
License: MIT
Keywords: biosynthesis,metabolic pathway,natural product,cheminformatics
Platform: UNKNOWN
Classifier: Development Status :: 5 - Production/Stable
Classifier: License :: OSI Approved :: MIT License
Classifier: Operating System :: Microsoft :: Windows :: Windows 10
Classifier: Operating System :: MacOS :: MacOS X
Classifier: Operating System :: POSIX :: Linux
Classifier: Programming Language :: Python :: 3.6
Classifier: Topic :: Scientific/Engineering :: Bio-Informatics
Classifier: Topic :: Scientific/Engineering :: Chemistry
Classifier: Topic :: Software Development :: Libraries :: Python Modules
Requires-Dist: cairosvg (~=2.4.2)
Requires-Dist: matplotlib (~=3.1.2)
Requires-Dist: networkx (==2.2)
